{
    "data":{
        "list":[
            {
                "name":"kerwin",
                "imageUrl":"https://img2.baidu.com/it/u=3850836080,2644658534&fm=253&fmt=auto&app=120&f=JPEG?w=166&h=166"
            },
            {
                "name":"kerwin",
                "imageUrl":"https://img2.baidu.com/it/u=3850836080,2644658534&fm=253&fmt=auto&app=120&f=JPEG?w=166&h=166"
            },
            {
                "name":"kerwin",
                "imageUrl":"https://img2.baidu.com/it/u=3850836080,2644658534&fm=253&fmt=auto&app=120&f=JPEG?w=166&h=166"
            },
            {
                "name":"kerwin",
                "imageUrl":"https://img2.baidu.com/it/u=3850836080,2644658534&fm=253&fmt=auto&app=120&f=JPEG?w=166&h=166"
            },
            {
                "name":"kerwin",
                "imageUrl":"https://img2.baidu.com/it/u=3850836080,2644658534&fm=253&fmt=auto&app=120&f=JPEG?w=166&h=166"
            }
        ]
    }
}